pplx/__init__.py
pplx/api.py
pplx-0.1.3.dist-info/LICENSE
pplx-0.1.3.dist-info/METADATA
pplx-0.1.3.dist-info/WHEEL
pplx-0.1.3.dist-info/entry_points.txt
pplx-0.1.3.dist-info/top_level.txt
pplx-0.1.3.dist-info/RECORD
