Metadata-Version: 2.1
Name: pplx
Version: 0.1.3
Summary: Ein Hilfsmodul für die Perplexity API
Home-page: https://github.com/Cinnay1621/pplx
Author: Yannic Basin
Author-email: yannicbasin@gmail.com
Classifier: Programming Language :: Python :: 3
Classifier: License :: OSI Approved :: MIT License
Classifier: Operating System :: OS Independent
Requires-Python: >=3.6
License-File: LICENSE
Requires-Dist: requests
